HISTORY.md
MANIFEST.in
README.md
setup.py
PyP100/PyL530.py
PyP100/PyP100.py
PyP100/PyP110.py
PyP100/__init__.py
PyP100/errorCodes.json
PyP100/tp_link_cipher.py
PyP100v2.egg-info/PKG-INFO
PyP100v2.egg-info/SOURCES.txt
PyP100v2.egg-info/dependency_links.txt
PyP100v2.egg-info/requires.txt
PyP100v2.egg-info/top_level.txt