Metadata-Version: 2.1
Name: PyP100v2
Version: 0.0.20
Summary: A module for controlling the Tp-link Tapo P100/P105/P110 plugs and L530/L510E bulbs.
Home-page: https://github.com/sangimed/TapoP100
Author: Toby Johnson
License: MIT
Download-URL: https://github.com/sangimed/TapoP100/archive/refs/tags/0.0.20.tar.gz
Keywords: Tapo,Tp-Link,P100
Platform: UNKNOWN
